Metadata-Version: 2.1
Name: httpfile-py
Version: 0.1.3
Summary: Python module loader for http file
Home-page: https://github.com/servicex-sh/httpfile-py
Author: linux_china
Author-email: libing.chen@gmail.com
License: Apache-2.0
Project-URL: Bug Tracker, https://github.com/servicex-sh/httpfile-py/issues
Project-URL: Documentation, https://github.com/servicex-sh/httpfile-py/
Project-URL: Source Code, https://github.com/servicex-sh/httpfile-py
Platform: UNKNOWN
Classifier: Environment :: Web Environment
Classifier: Intended Audience :: Developers
Classifier: Operating System :: OS Independent
Classifier: Topic :: Internet :: WWW/HTTP
Classifier: Framework :: AsyncIO
Classifier: Programming Language :: Python :: 3
Classifier: Programming Language :: Python :: 3.7
Classifier: Programming Language :: Python :: 3.8
Classifier: Programming Language :: Python :: 3.9
Classifier: Programming Language :: Python :: 3.10
Classifier: Programming Language :: Python :: 3 :: Only
Requires-Python: >=3.7
License-File: LICENSE
